jsdoc_parser/__init__.py
jsdoc_parser/cli.py
jsdoc_parser/composer.py
jsdoc_parser/parser.py
jsdoc_parser/utils.py
jsdoc_parser-0.1.1.dist-info/METADATA
jsdoc_parser-0.1.1.dist-info/WHEEL
jsdoc_parser-0.1.1.dist-info/entry_points.txt
jsdoc_parser-0.1.1.dist-info/top_level.txt
jsdoc_parser-0.1.1.dist-info/RECORD
