Metadata-Version: 2.4
Name: jsdoc-parser
Version: 0.1.1
Summary: A library for parsing and composing JSDoc strings
Author-email: Suman Saurabh <sumansaurabh@penify.dev>
License: MIT
Project-URL: Homepage, https://github.com/Penify-dev/jsdoc-parser
Project-URL: Bug Tracker, https://github.com/Penify-dev/jsdoc-parser/issues
Keywords: jsdoc,parser,docstring
Classifier: Programming Language :: Python :: 3
Classifier: License :: OSI Approved :: MIT License
Classifier: Operating System :: OS Independent
Requires-Python: >=3.7
